deezfacu/__dee_api__.py
deezfacu/__deegw_api__.py
deezfacu/__deezer_settings__.py
deezfacu/__download__.py
deezfacu/__download_utils__.py
deezfacu/__easy_spoty__.py
deezfacu/__init__.py
deezfacu/__others_settings__.py
deezfacu/__taggers__.py
deezfacu/__utils__.py
deezfacu/exceptions.py
deezfacu/models/__init__.py
deezfacu/models/album.py
deezfacu/models/playlist.py
deezfacu/models/preferences.py
deezfacu/models/smart.py
deezfacu/models/track.py
deezfacu-2021.8.31.data/scripts/deez-dw.py
deezfacu-2021.8.31.data/scripts/deez-web.py
deezloader/__dee_api__.py
deezloader/__deegw_api__.py
deezloader/__deezer_settings__.py
deezloader/__download__.py
deezloader/__download_utils__.py
deezloader/__easy_spoty__.py
deezloader/__init__.py
deezloader/__others_settings__.py
deezloader/__taggers__.py
deezloader/__utils__.py
deezloader/exceptions.py
deezloader/models/__init__.py
deezloader/models/album.py
deezloader/models/playlist.py
deezloader/models/preferences.py
deezloader/models/smart.py
deezloader/models/track.py
deezfacu-2021.8.31.dist-info/METADATA
deezfacu-2021.8.31.dist-info/WHEEL
deezfacu-2021.8.31.dist-info/top_level.txt
deezfacu-2021.8.31.dist-info/RECORD
