Metadata-Version: 2.1
Name: deezfacu
Version: 2021.8.31
Summary: Downloads songs, albums or playlists from deezer
Home-page: https://github.com/An0nimia/deezloader
Author: An0nimia
Author-email: An0nimia@protonmail.com
License: CC BY-NC-SA 4.0
Platform: UNKNOWN
Requires-Python: >=3.9
Requires-Dist: mutagen
Requires-Dist: pycryptodome
Requires-Dist: requests
Requires-Dist: spotipy
Requires-Dist: tqdm
Requires-Dist: fastapi
Requires-Dist: uvicorn[standard]
